PySimpleDB/__init__.py
PySimpleDB-0.2.1.dist-info/METADATA
PySimpleDB-0.2.1.dist-info/WHEEL
PySimpleDB-0.2.1.dist-info/top_level.txt
PySimpleDB-0.2.1.dist-info/RECORD
