Metadata-Version: 2.1
Name: PySimpleDB
Version: 0.2.1
Summary: Simple json database
Home-page: https://github.com/SuperZombi/Py-Simple-DB
Author: Super_Zombi
Author-email: super.zombi.yt@gmail.com
License: UNKNOWN
Platform: UNKNOWN
Classifier: Programming Language :: Python :: 3
Classifier: License :: OSI Approved :: MIT License
Classifier: Operating System :: OS Independent
Requires-Python: >=3.6
